_movici_geo_query.cp310-win_amd64.pyd
movici_geo_query/__init__.py
movici_geo_query/geo_query.py
movici_geo_query/geometry.py
movici_geo_query-1.1.1.dist-info/LICENSE
movici_geo_query-1.1.1.dist-info/METADATA
movici_geo_query-1.1.1.dist-info/WHEEL
movici_geo_query-1.1.1.dist-info/top_level.txt
movici_geo_query-1.1.1.dist-info/RECORD
